nonebot_plugin_xjj_video/__init__.py
nonebot_plugin_xjj_video-0.1.5.dist-info/METADATA
nonebot_plugin_xjj_video-0.1.5.dist-info/WHEEL
nonebot_plugin_xjj_video-0.1.5.dist-info/RECORD
