Metadata-Version: 2.1
Name: nonebot_plugin_xjj_video
Version: 0.1.5
Summary: 美女视频发送到聊天软件
License: MIT
Author: Endless-Path
Author-email: rk.chensiyu@gmail.com
Requires-Python: >=3.10,<4.0
Classifier: License :: OSI Approved :: MIT License
Classifier: Programming Language :: Python :: 3
Classifier: Programming Language :: Python :: 3.10
Classifier: Programming Language :: Python :: 3.11
Classifier: Programming Language :: Python :: 3.12
Classifier: Programming Language :: Python :: 3.13
Requires-Dist: httpx (>=0.25.0,<0.26.0)
Requires-Dist: nonebot-adapter-onebot (>=2.3.0,<3.0.0)
Requires-Dist: nonebot2 (>=2.2.0,<3.0.0)
